twisterl-0.4.1.dist-info/METADATA
twisterl-0.4.1.dist-info/WHEEL
twisterl-0.4.1.dist-info/licenses/LICENSE
twisterl/__init__.py
twisterl/defaults.py
twisterl/envs/__init__.py
twisterl/nn/__init__.py
twisterl/nn/policy.py
twisterl/nn/utils.py
twisterl/rl/__init__.py
twisterl/rl/algorithm.py
twisterl/rl/az.py
twisterl/rl/ppo.py
twisterl/train.py
twisterl/twisterl.cpython-39-darwin.so
twisterl/utils.py
twisterl-0.4.1.dist-info/RECORD
