Metadata-Version: 2.4
Name: twisterl
Version: 0.4.1
Classifier: Programming Language :: Rust
Classifier: Programming Language :: Python :: Implementation :: CPython
Classifier: Programming Language :: Python :: Implementation :: PyPy
Requires-Dist: torch>=2.2
Requires-Dist: loguru>=0.7
Requires-Dist: numpy>2.0
Requires-Dist: tensorboard>2.0
Requires-Dist: huggingface-hub>=0.34.4,<0.35.0
Requires-Dist: safetensors>=0.4
License-File: LICENSE
Summary: Minimal RL in Rust
Author: IBM Quantum+AI Team
Requires-Python: >=3.9
